cool_lib/__init__.py
cool_lib/__main__.py
cool_lib/a.py
cool_lib/b.py
cool_lib_test_123kes-0.1.dist-info/METADATA
cool_lib_test_123kes-0.1.dist-info/WHEEL
cool_lib_test_123kes-0.1.dist-info/entry_points.txt
cool_lib_test_123kes-0.1.dist-info/top_level.txt
cool_lib_test_123kes-0.1.dist-info/RECORD
