Metadata-Version: 2.1
Name: cool-lib-test-123kes
Version: 0.1
Summary: simples example in the python world
Home-page: https://github.com/gdamjan/hello-world-python-package
Author: x@x.com
Author-email: x@x.com
License: MIT
Platform: UNKNOWN
